{
    "Routes": [
        {
            "DestinationCidrBlock": "0.0.0.0/0",
            "TransitGatewayRouteTableAnnouncementId": "",
            "TransitGatewayAttachments": [
                {
                    "ResourceId": "tgw-00c51b4708a49e3c0",
                    "TransitGatewayAttachmentId": "tgw-attach-0886383021a3345b6",
                    "ResourceType": "peering"
                }
            ],
            "Type": "static",
            "State": "active"
        },
        {
            "DestinationCidrBlock": "10.107.0.0/16",
            "TransitGatewayRouteTableAnnouncementId": "",
            "TransitGatewayAttachments": [
                {
                    "ResourceId": "tgw-08ce130fec5a8960f",
                    "TransitGatewayAttachmentId": "tgw-attach-00ebbd69b2c46f7b1",
                    "ResourceType": "peering"
                }
            ],
            "Type": "static",
            "State": "active"
        },
        {
            "DestinationCidrBlock": "10.158.192.0/18",
            "TransitGatewayRouteTableAnnouncementId": "",
            "TransitGatewayAttachments": [
                {
                    "ResourceId": "vpc-0a0fb3ab856e73fa4",
                    "TransitGatewayAttachmentId": "tgw-attach-0cb09bfcfb9ebc838",
                    "ResourceType": "vpc"
                }
            ],
            "Type": "propagated",
            "State": "active"
        },
        {
            "DestinationCidrBlock": "10.159.128.0/19",
            "TransitGatewayRouteTableAnnouncementId": "",
            "TransitGatewayAttachments": [
                {
                    "ResourceId": "tgw-08ce130fec5a8960f",
                    "TransitGatewayAttachmentId": "tgw-attach-00ebbd69b2c46f7b1",
                    "ResourceType": "peering"
                }
            ],
            "Type": "static",
            "State": "active"
        },
        {
            "DestinationCidrBlock": "10.159.160.0/20",
            "TransitGatewayRouteTableAnnouncementId": "",
            "TransitGatewayAttachments": [
                {
                    "ResourceId": "tgw-08ce130fec5a8960f",
                    "TransitGatewayAttachmentId": "tgw-attach-00ebbd69b2c46f7b1",
                    "ResourceType": "peering"
                }
            ],
            "Type": "static",
            "State": "active"
        },
        {
            "DestinationCidrBlock": "10.159.224.0/19",
            "TransitGatewayRouteTableAnnouncementId": "",
            "TransitGatewayAttachments": [
                {
                    "ResourceId": "tgw-025766b1f30ab631a",
                    "TransitGatewayAttachmentId": "tgw-attach-0a51388aa94e53510",
                    "ResourceType": "peering"
                }
            ],
            "Type": "static",
            "State": "active"
        },
        {
            "DestinationCidrBlock": "10.159.64.0/18",
            "TransitGatewayRouteTableAnnouncementId": "",
            "TransitGatewayAttachments": [
                {
                    "ResourceId": "vpc-0a0fb3ab856e73fa4",
                    "TransitGatewayAttachmentId": "tgw-attach-0cb09bfcfb9ebc838",
                    "ResourceType": "vpc"
                }
            ],
            "Type": "propagated",
            "State": "active"
        },
        {
            "DestinationCidrBlock": "142.250.21.94/32",
            "TransitGatewayRouteTableAnnouncementId": "",
            "TransitGatewayAttachments": [
                {
                    "ResourceId": "vpc-0a0fb3ab856e73fa4",
                    "TransitGatewayAttachmentId": "tgw-attach-0cb09bfcfb9ebc838",
                    "ResourceType": "vpc"
                }
            ],
            "Type": "static",
            "State": "active"
        }
    ],
    "AdditionalRoutesAvailable": false
}
